{
  "schema_version": "1.0",
  "method_name": "tfidf_text",
  "pipeline_name": "tfidf",
  "config": {
    "use_propagated_terms": true,
    "ic_threshold": 1.5,
    "top_k": 10,
    "use_canonical_profiles": true
  },
  "stats": {
    "n_patient_terms_raw": 3,
    "n_patient_terms_propagated": 14,
    "n_patient_terms_used": 5,
    "n_diseases_scored": 19547,
    "n_diseases_skipped": 9,
    "computation_time_seconds": 0.3863
  },
  "rankings": [
    {
      "rank": 1,
      "disease_id": "ORPHA:247765",
      "label": "X-linked cerebellar ataxia",
      "profile_type": "category",
      "category_path": [
        {
          "disease_id": "ORPHA:557492",
          "label": "Group of disorders",
          "profile_type": null,
          "profile_type_label": null
        }
      ],
      "score": 0.575354,
      "method_name": "tfidf_text",
      "explanation": {
        "summary": "2 of 5 patient text tokens matched disease description (40% patient / 67% disease token coverage, 3 disease tokens total). Warning: disease description is very short — score may be unreliable.",
        "coverage": {
          "coverage_type": "token",
          "patient_token_coverage": 0.4,
          "disease_token_coverage": 0.6667,
          "direction_asymmetry": 0.2667,
          "n_patient_tokens": 5,
          "n_disease_tokens": 3,
          "n_matched_tokens": 2,
          "n_unmatched_patient_tokens": 3,
          "sparse_disease_description": true
        },
        "matched_terms": [
          {
            "token": "cerebellar",
            "idf_weight": 4.2901,
            "match_score": 1.0
          },
          {
            "token": "ataxia",
            "idf_weight": 3.8624,
            "match_score": 1.0
          }
        ],
        "unmatched_patient_terms": [
          {
            "token": "anemia",
            "idf_weight": 4.2146
          },
          {
            "token": "delay",
            "idf_weight": 3.3172
          },
          {
            "token": "developmental",
            "idf_weight": 3.0299
          }
        ],
        "method_specific": {
          "tfidf_mode": "tfidf_text",
          "coverage_unit": "tokens",
          "idf_weighted_matches": [
            {
              "id": "cerebellar",
              "label": "cerebellar",
              "idf_weight": 4.2901
            },
            {
              "id": "ataxia",
              "label": "ataxia",
              "idf_weight": 3.8624
            }
          ],
          "low_idf_matches": [],
          "n_low_idf_matches": 0,
          "low_idf_threshold": 0.5,
          "vector_norms": {
            "dot_product": 33.323008,
            "patient_norm": 8.442136,
            "disease_norm": 6.860519,
            "score_check": 0.575354
          },
          "sparse_disease_threshold": true
        },
        "diagnostics": {
          "raw_score": 0.575354,
          "tfidf_mode": "tfidf_text",
          "low_idf_threshold_applied": 0.5,
          "n_patient_vector_terms": 5,
          "n_disease_vector_terms": 3,
          "disease_used_label_fallback": false
        }
      }
    },
    {
      "rank": 2,
      "disease_id": "OMIM:617643",
      "label": "Cerebellar atrophy, developmental delay, and seizures",
      "profile_type": null,
      "category_path": [],
      "score": 0.56198,
      "method_name": "tfidf_text",
      "explanation": {
        "summary": "3 of 5 patient text tokens matched disease description (60% patient / 60% disease token coverage, 5 disease tokens total).",
        "coverage": {
          "coverage_type": "token",
          "patient_token_coverage": 0.6,
          "disease_token_coverage": 0.6,
          "direction_asymmetry": 0.0,
          "n_patient_tokens": 5,
          "n_disease_tokens": 5,
          "n_matched_tokens": 3,
          "n_unmatched_patient_tokens": 2,
          "sparse_disease_description": true
        },
        "matched_terms": [
          {
            "token": "cerebellar",
            "idf_weight": 4.2901,
            "match_score": 1.0
          },
          {
            "token": "delay",
            "idf_weight": 3.3172,
            "match_score": 1.0
          },
          {
            "token": "developmental",
            "idf_weight": 3.0299,
            "match_score": 1.0
          }
        ],
        "unmatched_patient_terms": [
          {
            "token": "anemia",
            "idf_weight": 4.2146
          },
          {
            "token": "ataxia",
            "idf_weight": 3.8624
          }
        ],
        "method_specific": {
          "tfidf_mode": "tfidf_text",
          "coverage_unit": "tokens",
          "idf_weighted_matches": [
            {
              "id": "cerebellar",
              "label": "cerebellar",
              "idf_weight": 4.2901
            },
            {
              "id": "delay",
              "label": "delay",
              "idf_weight": 3.3172
            },
            {
              "id": "developmental",
              "label": "developmental",
              "idf_weight": 3.0299
            }
          ],
          "low_idf_matches": [],
          "n_low_idf_matches": 0,
          "low_idf_threshold": 0.5,
          "vector_norms": {
            "dot_product": 38.588235,
            "patient_norm": 8.442136,
            "disease_norm": 8.133581,
            "score_check": 0.56198
          },
          "sparse_disease_threshold": false
        },
        "diagnostics": {
          "raw_score": 0.56198,
          "tfidf_mode": "tfidf_text",
          "low_idf_threshold_applied": 0.5,
          "n_patient_vector_terms": 5,
          "n_disease_vector_terms": 5,
          "disease_used_label_fallback": true
        }
      }
    },
    {
      "rank": 3,
      "disease_id": "MONDO:0060551",
      "label": "cerebellar atrophy, developmental delay, and seizures",
      "profile_type": null,
      "category_path": [],
      "score": 0.56198,
      "method_name": "tfidf_text",
      "explanation": {
        "summary": "3 of 5 patient text tokens matched disease description (60% patient / 60% disease token coverage, 5 disease tokens total).",
        "coverage": {
          "coverage_type": "token",
          "patient_token_coverage": 0.6,
          "disease_token_coverage": 0.6,
          "direction_asymmetry": 0.0,
          "n_patient_tokens": 5,
          "n_disease_tokens": 5,
          "n_matched_tokens": 3,
          "n_unmatched_patient_tokens": 2,
          "sparse_disease_description": true
        },
        "matched_terms": [
          {
            "token": "cerebellar",
            "idf_weight": 4.2901,
            "match_score": 1.0
          },
          {
            "token": "delay",
            "idf_weight": 3.3172,
            "match_score": 1.0
          },
          {
            "token": "developmental",
            "idf_weight": 3.0299,
            "match_score": 1.0
          }
        ],
        "unmatched_patient_terms": [
          {
            "token": "anemia",
            "idf_weight": 4.2146
          },
          {
            "token": "ataxia",
            "idf_weight": 3.8624
          }
        ],
        "method_specific": {
          "tfidf_mode": "tfidf_text",
          "coverage_unit": "tokens",
          "idf_weighted_matches": [
            {
              "id": "cerebellar",
              "label": "cerebellar",
              "idf_weight": 4.2901
            },
            {
              "id": "delay",
              "label": "delay",
              "idf_weight": 3.3172
            },
            {
              "id": "developmental",
              "label": "developmental",
              "idf_weight": 3.0299
            }
          ],
          "low_idf_matches": [],
          "n_low_idf_matches": 0,
          "low_idf_threshold": 0.5,
          "vector_norms": {
            "dot_product": 38.588235,
            "patient_norm": 8.442136,
            "disease_norm": 8.133581,
            "score_check": 0.56198
          },
          "sparse_disease_threshold": false
        },
        "diagnostics": {
          "raw_score": 0.56198,
          "tfidf_mode": "tfidf_text",
          "low_idf_threshold_applied": 0.5,
          "n_patient_vector_terms": 5,
          "n_disease_vector_terms": 5,
          "disease_used_label_fallback": true
        }
      }
    },
    {
      "rank": 4,
      "disease_id": "MONDO:0060745",
      "label": "intellectual developmental disorder with or without epilepsy or cerebellar ataxia",
      "profile_type": null,
      "category_path": [],
      "score": 0.561145,
      "method_name": "tfidf_text",
      "explanation": {
        "summary": "3 of 5 patient text tokens matched disease description (60% patient / 50% disease token coverage, 6 disease tokens total).",
        "coverage": {
          "coverage_type": "token",
          "patient_token_coverage": 0.6,
          "disease_token_coverage": 0.5,
          "direction_asymmetry": 0.1,
          "n_patient_tokens": 5,
          "n_disease_tokens": 6,
          "n_matched_tokens": 3,
          "n_unmatched_patient_tokens": 2,
          "sparse_disease_description": true
        },
        "matched_terms": [
          {
            "token": "cerebellar",
            "idf_weight": 4.2901,
            "match_score": 1.0
          },
          {
            "token": "ataxia",
            "idf_weight": 3.8624,
            "match_score": 1.0
          },
          {
            "token": "developmental",
            "idf_weight": 3.0299,
            "match_score": 1.0
          }
        ],
        "unmatched_patient_terms": [
          {
            "token": "anemia",
            "idf_weight": 4.2146
          },
          {
            "token": "delay",
            "idf_weight": 3.3172
          }
        ],
        "method_specific": {
          "tfidf_mode": "tfidf_text",
          "coverage_unit": "tokens",
          "idf_weighted_matches": [
            {
              "id": "cerebellar",
              "label": "cerebellar",
              "idf_weight": 4.2901
            },
            {
              "id": "ataxia",
              "label": "ataxia",
              "idf_weight": 3.8624
            },
            {
              "id": "developmental",
              "label": "developmental",
              "idf_weight": 3.0299
            }
          ],
          "low_idf_matches": [],
          "n_low_idf_matches": 0,
          "low_idf_threshold": 0.5,
          "vector_norms": {
            "dot_product": 42.503014,
            "patient_norm": 8.442136,
            "disease_norm": 8.972065,
            "score_check": 0.561145
          },
          "sparse_disease_threshold": false
        },
        "diagnostics": {
          "raw_score": 0.561145,
          "tfidf_mode": "tfidf_text",
          "low_idf_threshold_applied": 0.5,
          "n_patient_vector_terms": 5,
          "n_disease_vector_terms": 6,
          "disease_used_label_fallback": true
        }
      }
    },
    {
      "rank": 5,
      "disease_id": "OMIM:618501",
      "label": "Cerebellar atrophy with seizures and variable developmental delay",
      "profile_type": null,
      "category_path": [],
      "score": 0.516233,
      "method_name": "tfidf_text",
      "explanation": {
        "summary": "3 of 5 patient text tokens matched disease description (60% patient / 50% disease token coverage, 6 disease tokens total).",
        "coverage": {
          "coverage_type": "token",
          "patient_token_coverage": 0.6,
          "disease_token_coverage": 0.5,
          "direction_asymmetry": 0.1,
          "n_patient_tokens": 5,
          "n_disease_tokens": 6,
          "n_matched_tokens": 3,
          "n_unmatched_patient_tokens": 2,
          "sparse_disease_description": true
        },
        "matched_terms": [
          {
            "token": "cerebellar",
            "idf_weight": 4.2901,
            "match_score": 1.0
          },
          {
            "token": "delay",
            "idf_weight": 3.3172,
            "match_score": 1.0
          },
          {
            "token": "developmental",
            "idf_weight": 3.0299,
            "match_score": 1.0
          }
        ],
        "unmatched_patient_terms": [
          {
            "token": "anemia",
            "idf_weight": 4.2146
          },
          {
            "token": "ataxia",
            "idf_weight": 3.8624
          }
        ],
        "method_specific": {
          "tfidf_mode": "tfidf_text",
          "coverage_unit": "tokens",
          "idf_weighted_matches": [
            {
              "id": "cerebellar",
              "label": "cerebellar",
              "idf_weight": 4.2901
            },
            {
              "id": "delay",
              "label": "delay",
              "idf_weight": 3.3172
            },
            {
              "id": "developmental",
              "label": "developmental",
              "idf_weight": 3.0299
            }
          ],
          "low_idf_matches": [],
          "n_low_idf_matches": 0,
          "low_idf_threshold": 0.5,
          "vector_norms": {
            "dot_product": 38.588235,
            "patient_norm": 8.442136,
            "disease_norm": 8.85436,
            "score_check": 0.516233
          },
          "sparse_disease_threshold": false
        },
        "diagnostics": {
          "raw_score": 0.516233,
          "tfidf_mode": "tfidf_text",
          "low_idf_threshold_applied": 0.5,
          "n_patient_vector_terms": 5,
          "n_disease_vector_terms": 6,
          "disease_used_label_fallback": true
        }
      }
    },
    {
      "rank": 6,
      "disease_id": "MONDO:0032788",
      "label": "cerebellar atrophy with seizures and variable developmental delay",
      "profile_type": null,
      "category_path": [],
      "score": 0.516233,
      "method_name": "tfidf_text",
      "explanation": {
        "summary": "3 of 5 patient text tokens matched disease description (60% patient / 50% disease token coverage, 6 disease tokens total).",
        "coverage": {
          "coverage_type": "token",
          "patient_token_coverage": 0.6,
          "disease_token_coverage": 0.5,
          "direction_asymmetry": 0.1,
          "n_patient_tokens": 5,
          "n_disease_tokens": 6,
          "n_matched_tokens": 3,
          "n_unmatched_patient_tokens": 2,
          "sparse_disease_description": true
        },
        "matched_terms": [
          {
            "token": "cerebellar",
            "idf_weight": 4.2901,
            "match_score": 1.0
          },
          {
            "token": "delay",
            "idf_weight": 3.3172,
            "match_score": 1.0
          },
          {
            "token": "developmental",
            "idf_weight": 3.0299,
            "match_score": 1.0
          }
        ],
        "unmatched_patient_terms": [
          {
            "token": "anemia",
            "idf_weight": 4.2146
          },
          {
            "token": "ataxia",
            "idf_weight": 3.8624
          }
        ],
        "method_specific": {
          "tfidf_mode": "tfidf_text",
          "coverage_unit": "tokens",
          "idf_weighted_matches": [
            {
              "id": "cerebellar",
              "label": "cerebellar",
              "idf_weight": 4.2901
            },
            {
              "id": "delay",
              "label": "delay",
              "idf_weight": 3.3172
            },
            {
              "id": "developmental",
              "label": "developmental",
              "idf_weight": 3.0299
            }
          ],
          "low_idf_matches": [],
          "n_low_idf_matches": 0,
          "low_idf_threshold": 0.5,
          "vector_norms": {
            "dot_product": 38.588235,
            "patient_norm": 8.442136,
            "disease_norm": 8.85436,
            "score_check": 0.516233
          },
          "sparse_disease_threshold": false
        },
        "diagnostics": {
          "raw_score": 0.516233,
          "tfidf_mode": "tfidf_text",
          "low_idf_threshold_applied": 0.5,
          "n_patient_vector_terms": 5,
          "n_disease_vector_terms": 6,
          "disease_used_label_fallback": true
        }
      }
    },
    {
      "rank": 7,
      "disease_id": "ORPHA:98771",
      "label": "Spinocerebellar ataxia 18",
      "profile_type": null,
      "category_path": [
        {
          "disease_id": "ORPHA:557493",
          "label": "Disorder",
          "profile_type": null,
          "profile_type_label": null
        }
      ],
      "score": 0.486945,
      "method_name": "tfidf_text",
      "explanation": {
        "summary": "2 of 5 patient text tokens matched disease description (40% patient / 20% disease token coverage, 10 disease tokens total).",
        "coverage": {
          "coverage_type": "token",
          "patient_token_coverage": 0.4,
          "disease_token_coverage": 0.2,
          "direction_asymmetry": 0.2,
          "n_patient_tokens": 5,
          "n_disease_tokens": 10,
          "n_matched_tokens": 2,
          "n_unmatched_patient_tokens": 3,
          "sparse_disease_description": false
        },
        "matched_terms": [
          {
            "token": "cerebellar",
            "idf_weight": 4.2901,
            "match_score": 1.0
          },
          {
            "token": "ataxia",
            "idf_weight": 3.8624,
            "match_score": 1.0
          }
        ],
        "unmatched_patient_terms": [
          {
            "token": "anemia",
            "idf_weight": 4.2146
          },
          {
            "token": "delay",
            "idf_weight": 3.3172
          },
          {
            "token": "developmental",
            "idf_weight": 3.0299
          }
        ],
        "method_specific": {
          "tfidf_mode": "tfidf_text",
          "coverage_unit": "tokens",
          "idf_weighted_matches": [
            {
              "id": "cerebellar",
              "label": "cerebellar",
              "idf_weight": 4.2901
            },
            {
              "id": "ataxia",
              "label": "ataxia",
              "idf_weight": 3.8624
            }
          ],
          "low_idf_matches": [],
          "n_low_idf_matches": 0,
          "low_idf_threshold": 0.5,
          "vector_norms": {
            "dot_product": 81.564491,
            "patient_norm": 8.442136,
            "disease_norm": 19.84123,
            "score_check": 0.486945
          },
          "sparse_disease_threshold": false
        },
        "diagnostics": {
          "raw_score": 0.486945,
          "tfidf_mode": "tfidf_text",
          "low_idf_threshold_applied": 0.5,
          "n_patient_vector_terms": 5,
          "n_disease_vector_terms": 10,
          "disease_used_label_fallback": false
        }
      }
    },
    {
      "rank": 8,
      "disease_id": "ORPHA:101111",
      "label": "Spinocerebellar ataxia 25",
      "profile_type": null,
      "category_path": [
        {
          "disease_id": "ORPHA:557493",
          "label": "Disorder",
          "profile_type": null,
          "profile_type_label": null
        }
      ],
      "score": 0.475065,
      "method_name": "tfidf_text",
      "explanation": {
        "summary": "2 of 5 patient text tokens matched disease description (40% patient / 18% disease token coverage, 11 disease tokens total).",
        "coverage": {
          "coverage_type": "token",
          "patient_token_coverage": 0.4,
          "disease_token_coverage": 0.1818,
          "direction_asymmetry": 0.2182,
          "n_patient_tokens": 5,
          "n_disease_tokens": 11,
          "n_matched_tokens": 2,
          "n_unmatched_patient_tokens": 3,
          "sparse_disease_description": false
        },
        "matched_terms": [
          {
            "token": "cerebellar",
            "idf_weight": 4.2901,
            "match_score": 1.0
          },
          {
            "token": "ataxia",
            "idf_weight": 3.8624,
            "match_score": 1.0
          }
        ],
        "unmatched_patient_terms": [
          {
            "token": "anemia",
            "idf_weight": 4.2146
          },
          {
            "token": "delay",
            "idf_weight": 3.3172
          },
          {
            "token": "developmental",
            "idf_weight": 3.0299
          }
        ],
        "method_specific": {
          "tfidf_mode": "tfidf_text",
          "coverage_unit": "tokens",
          "idf_weighted_matches": [
            {
              "id": "cerebellar",
              "label": "cerebellar",
              "idf_weight": 4.2901
            },
            {
              "id": "ataxia",
              "label": "ataxia",
              "idf_weight": 3.8624
            }
          ],
          "low_idf_matches": [],
          "n_low_idf_matches": 0,
          "low_idf_threshold": 0.5,
          "vector_norms": {
            "dot_product": 81.564491,
            "patient_norm": 8.442136,
            "disease_norm": 20.337405,
            "score_check": 0.475065
          },
          "sparse_disease_threshold": false
        },
        "diagnostics": {
          "raw_score": 0.475065,
          "tfidf_mode": "tfidf_text",
          "low_idf_threshold_applied": 0.5,
          "n_patient_vector_terms": 5,
          "n_disease_vector_terms": 11,
          "disease_used_label_fallback": false
        }
      }
    },
    {
      "rank": 9,
      "disease_id": "ORPHA:98769",
      "label": "Spinocerebellar ataxia 15",
      "profile_type": null,
      "category_path": [
        {
          "disease_id": "ORPHA:557493",
          "label": "Disorder",
          "profile_type": null,
          "profile_type_label": null
        }
      ],
      "score": 0.470207,
      "method_name": "tfidf_text",
      "explanation": {
        "summary": "2 of 5 patient text tokens matched disease description (40% patient / 18% disease token coverage, 11 disease tokens total).",
        "coverage": {
          "coverage_type": "token",
          "patient_token_coverage": 0.4,
          "disease_token_coverage": 0.1818,
          "direction_asymmetry": 0.2182,
          "n_patient_tokens": 5,
          "n_disease_tokens": 11,
          "n_matched_tokens": 2,
          "n_unmatched_patient_tokens": 3,
          "sparse_disease_description": false
        },
        "matched_terms": [
          {
            "token": "cerebellar",
            "idf_weight": 4.2901,
            "match_score": 1.0
          },
          {
            "token": "ataxia",
            "idf_weight": 3.8624,
            "match_score": 1.0
          }
        ],
        "unmatched_patient_terms": [
          {
            "token": "anemia",
            "idf_weight": 4.2146
          },
          {
            "token": "delay",
            "idf_weight": 3.3172
          },
          {
            "token": "developmental",
            "idf_weight": 3.0299
          }
        ],
        "method_specific": {
          "tfidf_mode": "tfidf_text",
          "coverage_unit": "tokens",
          "idf_weighted_matches": [
            {
              "id": "cerebellar",
              "label": "cerebellar",
              "idf_weight": 4.2901
            },
            {
              "id": "ataxia",
              "label": "ataxia",
              "idf_weight": 3.8624
            }
          ],
          "low_idf_matches": [],
          "n_low_idf_matches": 0,
          "low_idf_threshold": 0.5,
          "vector_norms": {
            "dot_product": 81.564491,
            "patient_norm": 8.442136,
            "disease_norm": 20.547529,
            "score_check": 0.470207
          },
          "sparse_disease_threshold": false
        },
        "diagnostics": {
          "raw_score": 0.470207,
          "tfidf_mode": "tfidf_text",
          "low_idf_threshold_applied": 0.5,
          "n_patient_vector_terms": 5,
          "n_disease_vector_terms": 11,
          "disease_used_label_fallback": false
        }
      }
    },
    {
      "rank": 10,
      "disease_id": "ORPHA:139485",
      "label": "Coenzyme Q10 deficiency, primary, 4",
      "profile_type": null,
      "category_path": [
        {
          "disease_id": "ORPHA:557493",
          "label": "Disorder",
          "profile_type": null,
          "profile_type_label": null
        }
      ],
      "score": 0.463686,
      "method_name": "tfidf_text",
      "explanation": {
        "summary": "2 of 5 patient text tokens matched disease description (40% patient / 40% disease token coverage, 5 disease tokens total).",
        "coverage": {
          "coverage_type": "token",
          "patient_token_coverage": 0.4,
          "disease_token_coverage": 0.4,
          "direction_asymmetry": 0.0,
          "n_patient_tokens": 5,
          "n_disease_tokens": 5,
          "n_matched_tokens": 2,
          "n_unmatched_patient_tokens": 3,
          "sparse_disease_description": true
        },
        "matched_terms": [
          {
            "token": "cerebellar",
            "idf_weight": 4.2901,
            "match_score": 1.0
          },
          {
            "token": "ataxia",
            "idf_weight": 3.8624,
            "match_score": 1.0
          }
        ],
        "unmatched_patient_terms": [
          {
            "token": "anemia",
            "idf_weight": 4.2146
          },
          {
            "token": "delay",
            "idf_weight": 3.3172
          },
          {
            "token": "developmental",
            "idf_weight": 3.0299
          }
        ],
        "method_specific": {
          "tfidf_mode": "tfidf_text",
          "coverage_unit": "tokens",
          "idf_weighted_matches": [
            {
              "id": "cerebellar",
              "label": "cerebellar",
              "idf_weight": 4.2901
            },
            {
              "id": "ataxia",
              "label": "ataxia",
              "idf_weight": 3.8624
            }
          ],
          "low_idf_matches": [],
          "n_low_idf_matches": 0,
          "low_idf_threshold": 0.5,
          "vector_norms": {
            "dot_product": 33.323008,
            "patient_norm": 8.442136,
            "disease_norm": 8.512715,
            "score_check": 0.463686
          },
          "sparse_disease_threshold": false
        },
        "diagnostics": {
          "raw_score": 0.463686,
          "tfidf_mode": "tfidf_text",
          "low_idf_threshold_applied": 0.5,
          "n_patient_vector_terms": 5,
          "n_disease_vector_terms": 5,
          "disease_used_label_fallback": false
        }
      }
    }
  ]
}